llm_flaky/__init__.py
llm_flaky/plugin.py
llm_flaky-0.1.0.dist-info/METADATA
llm_flaky-0.1.0.dist-info/WHEEL
llm_flaky-0.1.0.dist-info/entry_points.txt
llm_flaky-0.1.0.dist-info/licenses/LICENSE
llm_flaky-0.1.0.dist-info/RECORD
