Metadata-Version: 2.4
Name: llm-flaky
Version: 0.1.0
Summary: Pytest plugin for running non-deterministic LLM tests with automatic retry and beautiful reports
Project-URL: Homepage, https://github.com/retailcrm/llm-flaky
Project-URL: Repository, https://github.com/retailcrm/llm-flaky
Project-URL: Issues, https://github.com/retailcrm/llm-flaky/issues
Project-URL: Changelog, https://github.com/retailcrm/llm-flaky/blob/main/CHANGELOG.md
Author-email: Ilyas Salikhov <salikhoff@gmail.com>
License-Expression: MIT
License-File: LICENSE
Keywords: ai,flaky,langchain,llm,openai,pytest,retry,testing
Classifier: Development Status :: 4 - Beta
Classifier: Framework :: Pytest
Classifier: Intended Audience :: Developers
Classifier: License :: OSI Approved :: MIT License
Classifier: Programming Language :: Python :: 3
Classifier: Programming Language :: Python :: 3.9
Classifier: Programming Language :: Python :: 3.10
Classifier: Programming Language :: Python :: 3.11
Classifier: Programming Language :: Python :: 3.12
Classifier: Programming Language :: Python :: 3.13
Classifier: Topic :: Scientific/Engineering :: Artificial Intelligence
Classifier: Topic :: Software Development :: Testing
Requires-Python: >=3.9
Requires-Dist: flaky>=3.7.0
Requires-Dist: pytest>=7.0.0
Provides-Extra: dev
Requires-Dist: build; extra == 'dev'
Requires-Dist: pytest-xdist; extra == 'dev'
Requires-Dist: ruff; extra == 'dev'
Requires-Dist: twine; extra == 'dev'
